up_splat/__init__.py
up_splat/run_for_prompt.py
up_splat-0.2.18.dist-info/METADATA
up_splat-0.2.18.dist-info/WHEEL
up_splat-0.2.18.dist-info/RECORD
