Metadata-Version: 2.1
Name: up-splat
Version: 0.2.18
Summary: 
Author: Julio Faerman
Author-email: jufaerma@redhat.com
Requires-Python: >=3.12,<4.0
Classifier: Programming Language :: Python :: 3
Requires-Dist: pluggy (>=1.3.0,<2.0.0)
